{
  "$defs": {
    "AccrualMethod": {
      "description": "Generic accrual method usable across instruments.\n\nThis mirrors the semantics of bond accrual methods but is defined at the\ncashflow layer so it can be reused by any instrument that exposes a\n`CashFlowSchedule`.",
      "oneOf": [
        {
          "const": "Linear",
          "description": "Linear accrual (simple interest interpolation).\n\n`Accrued = Coupon \u00d7 (elapsed / period)`",
          "type": "string"
        },
        {
          "const": "Compounded",
          "description": "Compounded accrual.\n\n`Accrued = N \u00d7 expm1(f \u00d7 ln1p(r))`\n\nwhich is the numerically stable form of\n`N \u00d7 [(1 + r)^f \u2212 1]`, where `r = coupon_amount / notional`\nand `f = elapsed / period` (time fraction within the current\ncoupon period).\n\n**Note:** ICMA Rule 251.1 prescribes *linear* accrual for bond\nAI calculations. This variant uses true exponential compounding\nand should not be cited as ICMA-style. It is intended for\ninstruments that genuinely compound within a coupon period\n(e.g. some leveraged loans).\n\n**Ex-coupon window convention:** inside an ex-coupon window the\naccrued interest is the negative rebate of the *remaining* stub,\ncompounded on the same basis:\n\n`Accrued = \u2212N \u00d7 expm1((1 \u2212 f) \u00d7 ln1p(r))`\n\nwhere `f = elapsed / period`. ICMA Rule 251.1 (and the UK DMO\ngilt convention) prescribe a *linear* ex-coupon rebate\n(`\u2212C \u00d7 (1 \u2212 f)`); use [`AccrualMethod::Linear`] for those markets.",
          "type": "string"
        }
      ]
    },
    "AmortizationSpec": {
      "description": "Amortization specification for principal over time.\n\nDescribes how principal amortizes or is exchanged during the life of the contract.\nUsed by instruments (e.g., bonds) and cashflow legs for consistent behavior.",
      "oneOf": [
        {
          "const": "None",
          "description": "No amortization \u2013 principal remains constant until final redemption.",
          "type": "string"
        },
        {
          "additionalProperties": false,
          "description": "Linear principal paydown towards a target final notional amount over all periods.",
          "properties": {
            "LinearTo": {
              "additionalProperties": false,
              "properties": {
                "final_notional": {
                  "$ref": "https://finstack_quant.dev/schemas/common/1/money.schema.json",
                  "description": "Target remaining principal at the end of the amortization schedule."
                }
              },
              "required": [
                "final_notional"
              ],
              "type": "object"
            }
          },
          "required": [
            "LinearTo"
          ],
          "type": "object"
        },
        {
          "additionalProperties": false,
          "description": "Explicit schedule of remaining principal amounts after given dates.\nEach pair stores `(date, remaining_principal_after_date)`.",
          "properties": {
            "StepRemaining": {
              "additionalProperties": false,
              "properties": {
                "schedule": {
                  "description": "Ordered list of `(date, remaining_principal_after_date)`.",
                  "items": {
                    "maxItems": 2,
                    "minItems": 2,
                    "prefixItems": [
                      {
                        "type": "string"
                      },
                      {
                        "$ref": "https://finstack_quant.dev/schemas/common/1/money.schema.json"
                      }
                    ],
                    "type": "array"
                  },
                  "type": "array"
                }
              },
              "required": [
                "schedule"
              ],
              "type": "object"
            }
          },
          "required": [
            "StepRemaining"
          ],
          "type": "object"
        },
        {
          "additionalProperties": false,
          "description": "Fixed percentage of **original** notional paid each period (capped by remaining outstanding).\n\nThis is a sinking-fund style amortization where the payment amount is constant\nacross periods: `initial_notional * pct`. It does **not** compound (i.e., it is\nNOT percentage-of-remaining / declining-balance / mortgage-style).",
          "properties": {
            "PercentOfOriginalPerPeriod": {
              "additionalProperties": false,
              "properties": {
                "pct": {
                  "description": "Fraction of original notional paid per period (e.g., 0.05 = 5%).",
                  "format": "double",
                  "type": "number"
                }
              },
              "required": [
                "pct"
              ],
              "type": "object"
            }
          },
          "required": [
            "PercentOfOriginalPerPeriod"
          ],
          "type": "object"
        },
        {
          "additionalProperties": false,
          "description": "Custom principal exchanges on specific dates (absolute cash amounts).\nPositive amounts reduce outstanding (i.e., principal paid by issuer).",
          "properties": {
            "CustomPrincipal": {
              "additionalProperties": false,
              "properties": {
                "items": {
                  "description": "List of `(date, principal_amount)` exchanges; amounts are absolute cashflows.",
                  "items": {
                    "maxItems": 2,
                    "minItems": 2,
                    "prefixItems": [
                      {
                        "type": "string"
                      },
                      {
                        "$ref": "https://finstack_quant.dev/schemas/common/1/money.schema.json"
                      }
                    ],
                    "type": "array"
                  },
                  "type": "array"
                }
              },
              "required": [
                "items"
              ],
              "type": "object"
            }
          },
          "required": [
            "CustomPrincipal"
          ],
          "type": "object"
        }
      ]
    },
    "CFKind": {
      "description": "Enumeration of cash-flow kinds for classification and ordering.\n\nUsed to distinguish between different types of cashflows for\nproper sequencing, risk calculation, and accounting treatment.\n\n# Sign Convention\n\nThe enum itself is **view agnostic**: individual instruments are\nresponsible for mapping these kinds into a holder or issuer view.\nBy convention in this crate:\n\n| Kind | Holder View (Long) | Issuer View (Short) |\n|------|-------------------|---------------------|\n| Interest (Fixed/Float) | Positive (receive) | Negative (pay) |\n| Notional (initial) | Negative (pay) | Positive (receive) |\n| Notional (final) | Positive (receive) | Negative (pay) |\n| Amortization | Positive (receive) | Negative (pay) |\n| PIK | Increases notional | Increases liability |\n| Fee | Negative (pay) | Positive (receive) |\n\nWhen constructing cashflow schedules, instruments should apply the appropriate\nsign based on the economic perspective being represented.\n\n# Cashflow Categories\n\nVariants are grouped by category:\n- **Interest**: `Fixed`, `FloatReset`, `Stub`\n- **Inflation**: `InflationCoupon`\n- **Fees**: `Fee`, `CommitmentFee`, `UsageFee`, `FacilityFee`\n- **Principal**: `Notional`, `PIK`, `Amortization`, `PrePayment`\n- **Revolving**: `RevolvingDraw`, `RevolvingRepayment`\n- **Credit Events**: `DefaultedNotional`, `Recovery`\n- **Margin/Collateral**: `InitialMarginPost`, `VariationMarginPay`, etc.",
      "oneOf": [
        {
          "const": "Fixed",
          "description": "Fixed-rate coupon cash-flow.\n\nPeriodic interest payment calculated as: `notional \u00d7 rate \u00d7 accrual_factor`.\nThe `rate` field on [`CashFlow`] stores the coupon rate used.",
          "type": "string"
        },
        {
          "const": "FloatReset",
          "description": "Floating-rate coupon cash-flow (or index fixing event).\n\nInterest payment based on a reference rate (e.g., SOFR, EURIBOR) plus spread.\nThe `reset_date` field on [`CashFlow`] indicates when the rate was fixed.\nThe `rate` field stores the all-in rate (index + spread) if known.",
          "type": "string"
        },
        {
          "const": "InflationCoupon",
          "description": "Inflation-linked coupon cash-flow.\n\nPeriodic coupon payment on an inflation-linked bond or swap leg where the\nreal coupon is multiplied by an index ratio (e.g., CPI / base CPI).\nThe `rate` field stores the real coupon rate when known.",
          "type": "string"
        },
        {
          "const": "Fee",
          "description": "Up-front fee or cost paid at inception.\n\nOne-time fee paid at trade date or settlement date, such as origination fees,\narrangement fees, or underwriting fees.",
          "type": "string"
        },
        {
          "const": "CommitmentFee",
          "description": "Commitment fee on undrawn balance.\n\nPeriodic fee charged on the undrawn portion of a revolving facility.\nTypically quoted in basis points per annum on the unused commitment.",
          "type": "string"
        },
        {
          "const": "UsageFee",
          "description": "Usage fee on drawn balance.\n\nAdditional fee charged when facility utilization exceeds a threshold,\ncommon in leveraged loan facilities.",
          "type": "string"
        },
        {
          "const": "FacilityFee",
          "description": "Facility fee on total commitment.\n\nFee charged on the entire committed amount regardless of utilization,\ncovering the lender's cost of keeping the facility available.",
          "type": "string"
        },
        {
          "const": "Notional",
          "description": "Principal exchange or notional flow.\n\nUsed for initial notional payment (at inception), final notional repayment\n(at maturity), or intermediate notional exchanges in cross-currency swaps.\nFor bonds: initial = purchase price, final = par redemption.",
          "type": "string"
        },
        {
          "const": "PIK",
          "description": "Payment-in-kind interest capitalization.\n\nInterest that is added to the outstanding principal rather than paid in cash.\nCreates a new notional amount: `new_notional = old_notional + PIK_interest`.\nThe amount field represents the interest capitalized.",
          "type": "string"
        },
        {
          "const": "Amortization",
          "description": "Scheduled amortization (principal repayment).\n\nReduces the outstanding principal per the amortization schedule.\nAmount is positive from holder perspective (principal returned).\nAfter amortization: `remaining_notional = previous_notional - amortization`.",
          "type": "string"
        },
        {
          "const": "PrePayment",
          "description": "Prepayment of principal (unscheduled early repayment).\n\nVoluntary or mandatory early return of principal, common in:\n- Mortgage-backed securities (borrower refinancing)\n- CLO/CDO structures (collateral prepayments)\n- Callable bonds (issuer exercise)",
          "type": "string"
        },
        {
          "const": "RevolvingDraw",
          "description": "Revolving facility draw (borrowing).\n\nIncrease in outstanding principal when borrower draws on a revolving facility.\nFrom holder (lender) view: negative (cash out to borrower).\nIncreases the drawn balance used for interest calculations.",
          "type": "string"
        },
        {
          "const": "RevolvingRepayment",
          "description": "Revolving facility repayment.\n\nDecrease in outstanding principal when borrower repays revolving facility.\nFrom holder (lender) view: positive (cash in from borrower).\nRestores availability under the commitment.",
          "type": "string"
        },
        {
          "const": "DefaultedNotional",
          "description": "Defaulted notional (principal written down due to credit event).\n\nRepresents the portion of principal that has experienced a credit event\n(failure to pay, bankruptcy, restructuring). Amount reflects the\nwrite-down from par.",
          "type": "string"
        },
        {
          "const": "Recovery",
          "description": "Recovery cashflow from defaulted principal.\n\nAmount recovered through workout, liquidation, or settlement of defaulted\ndebt. Typically expressed as a percentage of defaulted notional\n(recovery rate \u00d7 defaulted amount).",
          "type": "string"
        },
        {
          "const": "AccruedOnDefault",
          "description": "Accrued-on-default interest (ISDA standard for CDS).\n\nInterest accrued but unpaid at the time of a credit event.\nUnder ISDA standard conventions, the protection buyer pays\nthe accrued premium from the last payment date to the default date.",
          "type": "string"
        },
        {
          "const": "Stub",
          "description": "Irregular stub period interest.\n\nInterest payment for a non-standard accrual period at the beginning (front stub)\nor end (back stub) of a schedule. May be short stub (< regular period) or\nlong stub (> regular period). Accrual factor reflects actual period length.",
          "type": "string"
        },
        {
          "const": "InitialMarginPost",
          "description": "Initial margin posting (collateral transfer out to counterparty).\n\nRepresents the posting of initial margin collateral under CSA or clearing\nhouse rules. The amount is typically calculated using SIMM, schedule-based,\nor haircut methodologies.",
          "type": "string"
        },
        {
          "const": "InitialMarginReturn",
          "description": "Initial margin return (collateral returned from counterparty).\n\nRepresents the return of previously posted initial margin when exposure\ndecreases or trade is terminated.",
          "type": "string"
        },
        {
          "const": "VariationMarginReceive",
          "description": "Variation margin received (positive VM payment to us).\n\nDaily or periodic mark-to-market payment received when exposure moves\nin our favor. Governed by CSA threshold, MTA, and rounding rules.",
          "type": "string"
        },
        {
          "const": "VariationMarginPay",
          "description": "Variation margin paid (negative VM payment from us).\n\nDaily or periodic mark-to-market payment made when exposure moves\nagainst us. Governed by CSA threshold, MTA, and rounding rules.",
          "type": "string"
        },
        {
          "const": "MarginInterest",
          "description": "Interest accrued on posted margin collateral.\n\nRepresents interest paid or received on cash collateral posted as margin.\nRate typically defined in CSA (e.g., Fed Funds, EONIA, SONIA).",
          "type": "string"
        },
        {
          "const": "CollateralSubstitutionIn",
          "description": "Collateral substitution inflow (replacement collateral received).\n\nWhen a counterparty substitutes one form of eligible collateral for another,\nthis represents the incoming replacement asset.",
          "type": "string"
        },
        {
          "const": "CollateralSubstitutionOut",
          "description": "Collateral substitution outflow (original collateral returned).\n\nWhen a counterparty substitutes collateral, this represents the return\nof the original collateral being replaced.",
          "type": "string"
        }
      ]
    },
    "CallPut": {
      "description": "Call or put option on a bond.\n\nRepresents a single call or put option with an exercise period and redemption price.\nCall options allow the issuer to redeem early; put options allow the holder to redeem early.\n\n# Examples\n\n```rust\nuse finstack_quant_valuations::instruments::fixed_income::bond::CallPut;\nuse finstack_quant_core::dates::Date;\nuse time::Month;\n\n// Discrete call option: issuer can redeem at 102% of par on Jan 1, 2027\nlet call = CallPut {\n    start_date: Date::from_calendar_date(2027, Month::January, 1).unwrap(),\n    end_date: Date::from_calendar_date(2027, Month::January, 1).unwrap(),\n    price_pct_of_par: 102.0,\n    make_whole: None,\n};\n```",
      "properties": {
        "end_date": {
          "description": "Last date when the option can be exercised, inclusive.\n\nUse the same value as `start_date` for one-day/discrete exercise.",
          "format": "date",
          "type": "string"
        },
        "make_whole": {
          "anyOf": [
            {
              "$ref": "#/$defs/MakeWholeSpec"
            },
            {
              "type": "null"
            }
          ],
          "description": "Optional make-whole call specification.\n\nWhen set, the call price is computed as:\n  `max(price_pct_of_par, PV of remaining cashflows at reference_rate + spread)`\n\nThis ensures the holder is compensated at treasury + spread for early redemption.\nCommon in investment-grade corporate and convertible bonds."
        },
        "price_pct_of_par": {
          "description": "Redemption price as percentage of par amount.",
          "format": "double",
          "type": "number"
        },
        "start_date": {
          "description": "First date when the option can be exercised.",
          "format": "date",
          "type": "string"
        }
      },
      "required": [
        "start_date",
        "end_date",
        "price_pct_of_par"
      ],
      "type": "object"
    },
    "CallPutSchedule": {
      "description": "Schedule of call and put options for a bond.\n\nContains lists of call and put options that can be exercised during the bond's life.\nUsed for pricing callable/putable bonds and calculating yield-to-worst.\n\n# Examples\n\n```rust\nuse finstack_quant_valuations::instruments::fixed_income::bond::{CallPut, CallPutSchedule};\nuse finstack_quant_core::dates::Date;\nuse time::Month;\n\nlet mut schedule = CallPutSchedule::default();\nschedule.calls.push(CallPut {\n    start_date: Date::from_calendar_date(2027, Month::January, 1).unwrap(),\n    end_date: Date::from_calendar_date(2027, Month::January, 1).unwrap(),\n    price_pct_of_par: 102.0,\n    make_whole: None,\n});\n```",
      "properties": {
        "calls": {
          "description": "Call options (issuer can redeem early).",
          "items": {
            "$ref": "#/$defs/CallPut"
          },
          "type": "array"
        },
        "puts": {
          "description": "Put options (holder can redeem early).",
          "items": {
            "$ref": "#/$defs/CallPut"
          },
          "type": "array"
        }
      },
      "required": [
        "calls",
        "puts"
      ],
      "type": "object"
    },
    "CashFlow": {
      "additionalProperties": false,
      "description": "A single dated cash-flow (payment or reset).\n\nRepresents a monetary flow at a specific date with metadata\nfor proper classification and risk calculation.",
      "properties": {
        "accrual": {
          "anyOf": [
            {
              "$ref": "#/$defs/CashFlowAccrual"
            },
            {
              "type": "null"
            }
          ],
          "description": "Optional contractual accrual metadata owned by this flow."
        },
        "accrual_factor": {
          "description": "Accrual factor used for coupon amount and sensitivity.",
          "format": "double",
          "type": "number"
        },
        "amount": {
          "$ref": "https://finstack_quant.dev/schemas/common/1/money.schema.json",
          "description": "Monetary amount including its currency."
        },
        "date": {
          "description": "Payment date (or payment date for principal/fee, or reset date for `CFKind::FloatReset`).",
          "format": "date",
          "type": "string"
        },
        "kind": {
          "$ref": "#/$defs/CFKind",
          "description": "Category/kind of cash-flow."
        },
        "rate": {
          "description": "Effective rate used to calculate this cashflow (None if not rate-based or unknown).\n\nFor interest/fees: the annual rate used in the calculation\nFor notional/amortization/PIK: typically None\n\nThis is stored at cashflow creation time when available.\nFor instruments with intra-period events (e.g., revolving credit with draws/repays),\nthis may represent a time-weighted average rate across sub-periods.",
          "format": "double",
          "type": [
            "number",
            "null"
          ]
        },
        "reset_date": {
          "description": "Optional index reset date (for floating coupons).",
          "format": "date",
          "type": [
            "string",
            "null"
          ]
        }
      },
      "required": [
        "date",
        "amount",
        "kind",
        "accrual_factor"
      ],
      "type": "object"
    },
    "CashFlowAccrual": {
      "additionalProperties": false,
      "description": "Contractual accrual metadata attached to one cashflow.",
      "properties": {
        "day_count": {
          "$ref": "https://finstack_quant.dev/schemas/common/1/day_count.schema.json",
          "description": "Day-count convention used for the accrual factor."
        },
        "end": {
          "description": "Contractual accrual-period end date.",
          "type": "string"
        },
        "projected_index_rate": {
          "description": "Projected index rate before spread, gearing, caps, or floors.",
          "format": "double",
          "type": [
            "number",
            "null"
          ]
        },
        "start": {
          "description": "Contractual accrual-period start date.",
          "type": "string"
        }
      },
      "required": [
        "start",
        "end",
        "day_count"
      ],
      "type": "object"
    },
    "CashFlowMeta": {
      "additionalProperties": false,
      "description": "Metadata shared by an entire cashflow schedule.\n\nTracks referenced calendar IDs, optional facility limits, and the instrument's\nissue date for use by downstream engines (e.g., accrual calculation).",
      "properties": {
        "calendar_ids": {
          "description": "Holiday calendar IDs used for schedule adjustments.",
          "items": {
            "type": "string"
          },
          "type": "array"
        },
        "facility_limit": {
          "anyOf": [
            {
              "$ref": "https://finstack_quant.dev/schemas/common/1/money.schema.json"
            },
            {
              "type": "null"
            }
          ],
          "description": "Optional facility limit/commitment for instruments like RCFs."
        },
        "issue_date": {
          "description": "Issue date of the instrument, when known.\n\nUsed by the accrual engine to establish the first coupon period start\ndate precisely, avoiding the inverse day count approximation that can\nbe off by 1-2 days.",
          "format": "date",
          "type": [
            "string",
            "null"
          ]
        },
        "maturity_date": {
          "description": "Contractual maturity date, distinct from an adjusted final payment date.",
          "format": "date",
          "type": [
            "string",
            "null"
          ]
        },
        "representation": {
          "$ref": "#/$defs/CashflowRepresentation",
          "default": "contractual",
          "description": "Meaning of the schedule relative to waterfall policy."
        }
      },
      "required": [
        "calendar_ids"
      ],
      "type": "object"
    },
    "CashFlowSchedule": {
      "additionalProperties": false,
      "description": "Cashflow schedule output from the composable builder.\n\nContains ordered cashflows plus notional and a representative `DayCount`.\nMethods provide convenient accessors commonly used by pricing and analysis.",
      "properties": {
        "day_count": {
          "$ref": "https://finstack_quant.dev/schemas/common/1/day_count.schema.json",
          "description": "Day count convention for interest calculations"
        },
        "flows": {
          "description": "Ordered cashflows (coupons, principal payments, fees)",
          "items": {
            "$ref": "#/$defs/CashFlow"
          },
          "type": "array"
        },
        "meta": {
          "$ref": "#/$defs/CashFlowMeta",
          "description": "Additional metadata (calendars, facility limits)"
        },
        "notional": {
          "$ref": "#/$defs/Notional",
          "description": "Notional schedule (constant or amortizing)"
        }
      },
      "required": [
        "flows",
        "notional",
        "day_count",
        "meta"
      ],
      "type": "object"
    },
    "CashflowRepresentation": {
      "description": "Meaning of the emitted schedule relative to pricing and waterfall policy.",
      "oneOf": [
        {
          "const": "contractual",
          "description": "Fixed or contractually scheduled future dated cash amounts.",
          "type": "string"
        },
        {
          "const": "projected",
          "description": "Current-market or model-projected future dated cash amounts.",
          "type": "string"
        },
        {
          "const": "placeholder",
          "description": "Intentionally empty because the contingent payoff policy is not modeled yet.",
          "type": "string"
        },
        {
          "const": "no_residual",
          "description": "Intentionally empty because no future dated cashflows remain.",
          "type": "string"
        }
      ]
    },
    "CashflowSpec": {
      "description": "Thin facade over canonical builder coupon specs for bond cashflows.\n\nWraps `FixedCouponSpec` and `FloatingCouponSpec` from the cashflow builder,\nproviding convenience constructors with sensible defaults for common bond use cases.\nThis ensures parity with all builder features (floors/caps, BDC, calendars, PIK, etc.)\nwhile keeping the bond API simple.",
      "oneOf": [
        {
          "additionalProperties": false,
          "description": "Fixed-rate bond using the canonical `FixedCouponSpec`.",
          "properties": {
            "Fixed": {
              "$ref": "https://finstack_quant.dev/schemas/cashflow/1/coupon_specs.schema.json"
            }
          },
          "required": [
            "Fixed"
          ],
          "type": "object"
        },
        {
          "additionalProperties": false,
          "description": "Floating-rate note using the canonical `FloatingCouponSpec`.",
          "properties": {
            "Floating": {
              "$ref": "#/$defs/FloatingCouponSpec"
            }
          },
          "required": [
            "Floating"
          ],
          "type": "object"
        },
        {
          "additionalProperties": false,
          "description": "Step-up/step-down coupon bond with scheduled rate changes.",
          "properties": {
            "StepUp": {
              "$ref": "#/$defs/StepUpCouponSpec"
            }
          },
          "required": [
            "StepUp"
          ],
          "type": "object"
        },
        {
          "additionalProperties": false,
          "description": "Amortizing bond (principal payments during life).",
          "properties": {
            "Amortizing": {
              "properties": {
                "base": {
                  "$ref": "#/$defs/CashflowSpec",
                  "description": "Base cashflow specification (fixed or floating)."
                },
                "schedule": {
                  "$ref": "#/$defs/AmortizationSpec",
                  "description": "Amortization schedule."
                }
              },
              "required": [
                "base",
                "schedule"
              ],
              "type": "object"
            }
          },
          "required": [
            "Amortizing"
          ],
          "type": "object"
        }
      ]
    },
    "CouponType": {
      "description": "Coupon cashflow type for fixed/floating coupons.\n\n- `Cash`: 100% paid in cash.\n- `PIK`: 100% capitalized into principal.\n- `Split { cash_pct, pik_pct }`: percentages applied to the coupon amount.",
      "oneOf": [
        {
          "const": "Cash",
          "description": "Cash variant.",
          "type": "string"
        },
        {
          "const": "PIK",
          "description": "PIK variant.",
          "type": "string"
        },
        {
          "additionalProperties": false,
          "description": "Split variant.",
          "properties": {
            "Split": {
              "additionalProperties": false,
              "properties": {
                "cash_pct": {
                  "description": "Fraction of the coupon paid in cash, expressed as a decimal share in\n`[0, 1]`.",
                  "pattern": "^-?\\d+(\\.\\d+)?([eE][+-]?\\d+)?$",
                  "type": [
                    "string",
                    "number"
                  ]
                },
                "pik_pct": {
                  "description": "Fraction of the coupon capitalized as PIK, expressed as a decimal\nshare in `[0, 1]`.",
                  "pattern": "^-?\\d+(\\.\\d+)?([eE][+-]?\\d+)?$",
                  "type": [
                    "string",
                    "number"
                  ]
                }
              },
              "required": [
                "cash_pct",
                "pik_pct"
              ],
              "type": "object"
            }
          },
          "required": [
            "Split"
          ],
          "type": "object"
        }
      ]
    },
    "FloatingCouponSpec": {
      "additionalProperties": false,
      "description": "Floating coupon specification (composes FloatingRateSpec).\n\nUsed by the cashflow builder for instruments with floating rate coupons.\nEmbeds the canonical `FloatingRateSpec` for rate projection and adds\ncoupon-specific settings like payment frequency and PIK behavior.",
      "properties": {
        "adjust_accrual_dates": {
          "description": "Whether accrual-period boundaries are business-day adjusted with `bdc`.\n\n- `false` (default, bond convention): accrual periods run between the\n  unadjusted schedule anchors; only payment dates roll.\n- `true` (swap convention, ISDA 2006 \u00a74.10 / ARRC SOFR conventions):\n  both accrual-period boundaries are rolled with `bdc` before year\n  fractions and overnight observation windows are computed. The swap\n  presets ([`Self::usd_sofr_swap`], [`Self::eur_estr_swap`],\n  [`Self::gbp_sonia_swap`], [`Self::jpy_tona_swap`]) set this to\n  `true`.\n\nSerialized only when `true`, so existing wire payloads are unchanged.",
          "type": "boolean"
        },
        "bdc": {
          "$ref": "https://finstack_quant.dev/schemas/common/1/business_day_convention.schema.json",
          "default": "modified_following",
          "description": "Business-day convention applied when rolling **payment dates** onto\nvalid business days.\n\nAccrual boundaries are left unadjusted (bond/ICMA convention) unless\n[`Self::adjust_accrual_dates`] is `true`, in which case the same\nconvention also rolls both accrual-period boundaries (swap/ISDA 2006\n\u00a74.10 convention)."
        },
        "calendar_id": {
          "description": "Holiday calendar identifier used together with `bdc`.\n\nUse `\"weekends_only\"` when only Saturday/Sunday adjustment is needed.",
          "type": "string"
        },
        "coupon_type": {
          "$ref": "#/$defs/CouponType",
          "default": "Cash",
          "description": "Coupon type (Cash/PIK/Split)."
        },
        "dc": {
          "$ref": "https://finstack_quant.dev/schemas/common/1/day_count.schema.json",
          "description": "Day-count convention used to convert each generated accrual period into a\nyear fraction."
        },
        "end_of_month": {
          "default": false,
          "description": "Whether end-of-month rolling should be preserved when generating the\nschedule.",
          "type": "boolean"
        },
        "freq": {
          "$ref": "https://finstack_quant.dev/schemas/common/1/tenor.schema.json",
          "description": "Accrual and payment frequency used to generate the schedule boundaries."
        },
        "payment_lag_days": {
          "default": 0,
          "description": "Payment lag in business days after the adjusted accrual end date.",
          "format": "int32",
          "type": "integer"
        },
        "rate_spec": {
          "$ref": "#/$defs/FloatingRateSpec",
          "description": "Floating rate specification (contains index, spread, floor, cap, etc)."
        },
        "stub": {
          "$ref": "#/$defs/StubKind",
          "default": "ShortFront",
          "description": "Stub-handling rule used when the start/end dates do not fit an exact\nwhole number of periods."
        }
      },
      "required": [
        "rate_spec",
        "freq",
        "dc",
        "calendar_id"
      ],
      "type": "object"
    },
    "FloatingRateFallback": {
      "description": "Policy for handling floating rate projection failures.\n\nControls what happens when a forward curve lookup fails during\ncashflow emission. The default (`Error`) surfaces failures explicitly;\nthe other variants are explicit opt-in degradation modes for callers\nthat intentionally want a projected schedule without a forward curve.\n\n# References\n\n- `docs/REFERENCES.md#andersen-piterbarg-interest-rate-modeling`\n- `docs/REFERENCES.md#hull-options-futures`",
      "oneOf": [
        {
          "const": "Error",
          "description": "Return an error with curve ID and reset date (strictest, safest).",
          "type": "string"
        },
        {
          "const": "SpreadOnly",
          "description": "Treat the index component as zero, so the coupon rate is the spread\n(plus any floors/caps/gearing). An explicit opt-in for spread-only\nprojection when no forward curve is available; emits `warn!`.",
          "type": "string"
        },
        {
          "additionalProperties": false,
          "description": "Use a fixed rate as the index component. Emits `info!`.\n\nThe value is a **decimal annual rate**, not basis points: `0.045`\nmeans 4.5%. This differs from the bp-denominated spread/floor/cap\nfields on [`FloatingRateSpec`] because it substitutes directly for\nthe projected index rate.",
          "properties": {
            "FixedRate": {
              "pattern": "^-?\\d+(\\.\\d+)?([eE][+-]?\\d+)?$",
              "type": [
                "string",
                "number"
              ]
            }
          },
          "required": [
            "FixedRate"
          ],
          "type": "object"
        }
      ]
    },
    "FloatingRateSpec": {
      "additionalProperties": false,
      "description": "Canonical floating rate specification for all instruments.\n\nUsed by bonds, swaps, credit facilities, and structured products.\nAll instruments should compose this type rather than defining their own\nfloating rate specifications.\n\n# Rate Calculation\n\nThe all-in rate is computed as:\n1. Look up forward rate from `index_id` curve for the accrual period\n2. Apply `index_floor_bp` to index rate (if specified) - applied BEFORE adding spread\n3. Add `spread_bp` to get base rate\n4. Multiply by `gearing` (typically 1.0)\n5. Apply `all_in_cap_bp` to final rate (if specified) - applied AFTER spread and gearing\n\nFormula: `cap(gearing * (floor(index) + spread))`\n\n# Negative Rate Handling\n\nNegative index rates are supported and will flow through calculations\nunless constrained by floors. For markets with negative rates (EUR, JPY, CHF):\n\n- Set `index_floor_bp: Some(0.0)` to floor the index at zero\n- Set `all_in_floor_bp: Some(0.0)` to floor the total coupon at zero\n- Omit floors to allow negative coupons (rare but valid in some structures)\n\nThe implementation does not reject negative rates; the policy is controlled\nby the floor configuration.\n\n# Seasoned Instruments (Historical Fixings)\n\nHistorical fixings **are supported** via the `MarketContext`: store a\n`ScalarTimeSeries` under the canonical id `FIXING:{index_id}` (see\n`finstack_quant_core::market_data::fixings`) containing realized index\nobservations. Observation dates strictly before the forward curve base\ndate then resolve from that series instead of the curve:\n\n- **Overnight observations** (compounded/averaged paths) use LOCF lookup\n  (last observation carried forward), matching RFR publication\n  conventions where a fixing carries over non-publication days\n  (ARRC 2020 SOFR conventions; ISDA 2021 Supp. 70 \u00a77.1(g)). A partially\n  seasoned compounding window seamlessly mixes realized fixings and\n  curve-projected forwards with identical `(rate, days)` weighting.\n- **Term-rate resets** use exact-date lookup on the (business-day\n  adjusted) reset date \u2014 a term rate fixes on a specific published date.\n  The fixing is the index rate only; gearing/spread/floors/caps apply on\n  top exactly as for projected rates.\n\nAn observation exactly on the curve base date prefers a published\nsame-day fixing when the series has one, otherwise projects from `t = 0`.\n\nThe [`FloatingRateFallback`] policy applies only when **no** fixing\nseries is provided: `Error` (the default) fails the build with a\ndescriptive message naming the date, index, and expected series id;\n`FixedRate(r)` uses `r` as the index rate for the affected coupon;\n`SpreadOnly` projects spread-only.\n\n# Example\n\n```rust\nuse finstack_quant_core::dates::Tenor;\nuse finstack_quant_cashflows::builder::{FloatingRateSpec, OvernightIndexConstraintApplication};\nuse rust_decimal_macros::dec;\n\n// 3M SOFR + 200bps with 0% floor\nlet spec = FloatingRateSpec {\n    index_id: \"USD-SOFR-3M\".into(),\n    spread_bp: dec!(200.0),\n    gearing: dec!(1.0),\n    gearing_includes_spread: true,\n    index_floor_bp: Some(dec!(0.0)),\n    all_in_floor_bp: None,\n    all_in_cap_bp: None,\n    index_cap_bp: None,\n    overnight_index_constraints: OvernightIndexConstraintApplication::Daily,\n    reset_freq: Tenor::quarterly(),\n    index_tenor: None,\n    reset_lag_days: 2,\n    fixing_calendar_id: None,\n    overnight_compounding: None,\n    overnight_basis: None,\n    fallback: Default::default(),\n};\n```",
      "properties": {
        "all_in_cap_bp": {
          "default": null,
          "description": "Cap on all-in rate in basis points (applied after spread and gearing).\n\nExample: all_in_cap_bp = Some(1000.0) ensures all-in rate <= 10%.",
          "pattern": "^-?\\d+(\\.\\d+)?([eE][+-]?\\d+)?$",
          "type": [
            "string",
            "number",
            "null"
          ]
        },
        "all_in_floor_bp": {
          "default": null,
          "description": "Floor on all-in rate in basis points (Min Coupon).\n\nApplied to the final calculated rate after gearing and spread.",
          "pattern": "^-?\\d+(\\.\\d+)?([eE][+-]?\\d+)?$",
          "type": [
            "string",
            "number",
            "null"
          ]
        },
        "fallback": {
          "$ref": "#/$defs/FloatingRateFallback",
          "description": "Policy when forward curve lookup fails during emission.\n\nDefaults to `Error`, which surfaces curve lookup failures.\nSet to `SpreadOnly` for spread-only projection, or `FixedRate(r)`\nto use a fixed index rate."
        },
        "fixing_calendar_id": {
          "default": null,
          "description": "Optional calendar for rate fixing (reset lag).\n\nIf not provided, defaults to the coupon schedule calendar.",
          "type": [
            "string",
            "null"
          ]
        },
        "gearing": {
          "default": "1",
          "description": "Gearing/leverage multiplier applied to the all-in rate (default: 1.0).\n\nExample: gearing = 2.0 means the rate is doubled.\n\n**Restriction:** gearing must be strictly positive (`gearing > 0`);\nprojection rejects zero or negative gearing, so inverse floaters\n(negative gearing) are not currently expressible with this field.",
          "pattern": "^-?\\d+(\\.\\d+)?([eE][+-]?\\d+)?$",
          "type": [
            "string",
            "number"
          ]
        },
        "gearing_includes_spread": {
          "default": true,
          "description": "Whether gearing includes the spread (default: true).\n\n- `true`: `rate = (index + spread) * gearing`\n- `false`: `rate = (index * gearing) + spread` (Affine model)",
          "type": "boolean"
        },
        "index_cap_bp": {
          "default": null,
          "description": "Cap on index rate in basis points (applied to index component).",
          "pattern": "^-?\\d+(\\.\\d+)?([eE][+-]?\\d+)?$",
          "type": [
            "string",
            "number",
            "null"
          ]
        },
        "index_floor_bp": {
          "default": null,
          "description": "Floor on index rate in basis points (applied to index component).\n\nExample: index_floor_bp = Some(0.0) ensures index rate >= 0%.",
          "pattern": "^-?\\d+(\\.\\d+)?([eE][+-]?\\d+)?$",
          "type": [
            "string",
            "number",
            "null"
          ]
        },
        "index_id": {
          "$ref": "https://finstack_quant.dev/schemas/common/1/id.schema.json",
          "description": "Forward curve identifier (e.g., \"USD-SOFR-3M\", \"EUR-EURIBOR-6M\")."
        },
        "index_tenor": {
          "anyOf": [
            {
              "$ref": "https://finstack_quant.dev/schemas/common/1/tenor.schema.json"
            },
            {
              "type": "null"
            }
          ],
          "description": "Underlying index tenor used to project the forward rate (term rates).\n\nThe forward rate is projected over\n`[accrual_start, accrual_start + index_tenor]`. When `None` (the serde\ndefault), the index tenor falls back to [`Self::reset_freq`]. Set this\nexplicitly when the reset cadence differs from the index's underlying\ndeposit period (e.g. a monthly-paying leg referencing a 3M index).\nIgnored for overnight-compounded legs."
        },
        "overnight_basis": {
          "anyOf": [
            {
              "$ref": "https://finstack_quant.dev/schemas/common/1/day_count.schema.json"
            },
            {
              "type": "null"
            }
          ],
          "description": "Day-count basis for the overnight compounding denominator.\n\nThis controls the annualization factor used when compounding daily\novernight fixings (e.g., 360 for SOFR/ESTR/TONA, 365 for SONIA).\nIt is independent of the leg's accrual day count (`dc`), which\ngoverns the coupon year fraction.\n\nDefaults to `Act/360` when `None`, matching SOFR/ESTR/TONA\nconvention. Set to `Act/365F` for SONIA.\nIgnored when `overnight_compounding` is `None`."
        },
        "overnight_compounding": {
          "anyOf": [
            {
              "$ref": "#/$defs/OvernightCompoundingMethod"
            },
            {
              "type": "null"
            }
          ],
          "description": "Overnight compounding method for overnight rate indices (SOFR, ESTR, SONIA).\n\nWhen set to `Some(method)`, the rate for each accrual period is computed\nby compounding daily overnight fixings according to the specified method,\nrather than looking up a single forward rate for the period.\n\nLeave as `None` for term rates (e.g., 3M EURIBOR, 6M LIBOR)."
        },
        "overnight_index_constraints": {
          "$ref": "#/$defs/OvernightIndexConstraintApplication",
          "description": "Index floor/cap application policy for overnight-compounded coupons."
        },
        "reset_freq": {
          "$ref": "https://finstack_quant.dev/schemas/common/1/tenor.schema.json",
          "description": "Reset frequency for rate fixings.\n\nThis is the cadence at which the rate refixes; it also serves as the\ndefault index tenor when [`Self::index_tenor`] is `None`."
        },
        "reset_lag_days": {
          "default": 2,
          "description": "Reset lag in business days (e.g., 2 for T-2 SOFR convention).",
          "format": "int32",
          "type": "integer"
        },
        "spread_bp": {
          "description": "Spread/margin over index in basis points. Uses Decimal for exact representation.",
          "pattern": "^-?\\d+(\\.\\d+)?([eE][+-]?\\d+)?$",
          "type": [
            "string",
            "number"
          ]
        }
      },
      "required": [
        "index_id",
        "spread_bp",
        "reset_freq"
      ],
      "type": "object"
    },
    "IssuePrice": {
      "description": "Issue price = invested capital `V0` (amount funded at issue; IRR initial outflow\nand MOIC denominator).\n\nDefaults to [`IssuePrice::Par`] when not specified.",
      "oneOf": [
        {
          "const": "Par",
          "description": "Par notional (default). `V0 = notional`.",
          "type": "string"
        },
        {
          "additionalProperties": false,
          "description": "Explicit cash amount funded at issue. Must match the bond's notional currency.",
          "properties": {
            "Amount": {
              "$ref": "https://finstack_quant.dev/schemas/common/1/money.schema.json"
            }
          },
          "required": [
            "Amount"
          ],
          "type": "object"
        },
        {
          "additionalProperties": false,
          "description": "Percent of par, e.g. `98.0` for 2 points of original issue discount.\n`V0 = notional * pct / 100`.",
          "properties": {
            "PctOfPar": {
              "format": "double",
              "type": "number"
            }
          },
          "required": [
            "PctOfPar"
          ],
          "type": "object"
        }
      ]
    },
    "MakeWholeSpec": {
      "description": "Make-whole call specification.\n\nDefines the reference curve and spread used to compute the make-whole redemption\nprice. The issuer pays the holder the greater of par and the present value of\nremaining cashflows discounted at the reference rate plus a spread.\n\n# Industry Practice\n\n- Investment-grade corporates: typically Treasury + 25-50 bps\n- High-yield: typically Treasury + 50-100 bps\n- Convertibles: typically Treasury + 50 bps",
      "properties": {
        "reference_curve_id": {
          "$ref": "https://finstack_quant.dev/schemas/common/1/id.schema.json",
          "description": "Reference curve identifier (e.g., \"USD-TREASURY\")."
        },
        "spread_bps": {
          "description": "Spread over the reference curve in basis points (e.g., 50.0 = T+50bps).",
          "format": "double",
          "type": "number"
        }
      },
      "required": [
        "reference_curve_id",
        "spread_bps"
      ],
      "type": "object"
    },
    "Notional": {
      "additionalProperties": false,
      "description": "Notional amount with an optional amortisation rule.\n\nCombines initial principal with amortization behavior for complete\nnotional lifecycle management.",
      "properties": {
        "amort": {
          "$ref": "#/$defs/AmortizationSpec",
          "description": "Amortisation rule applied after each period."
        },
        "initial": {
          "$ref": "https://finstack_quant.dev/schemas/common/1/money.schema.json",
          "description": "Initial principal amount outstanding at leg inception."
        }
      },
      "required": [
        "initial",
        "amort"
      ],
      "type": "object"
    },
    "OvernightCompoundingMethod": {
      "description": "Compounding method for overnight rate indices (SOFR, ESTR, SONIA).\n\nControls how daily overnight fixings are aggregated into a period rate\nfor floating rate coupons. The choice of compounding method affects both\nthe accrued amount and the payment timing/certainty.\n\n# Market Conventions\n\n| Index | Standard Method | Lookback | Reference |\n|-------|----------------|----------|-----------|\n| USD SOFR | CompoundedInArrears | 2 BD | ISDA 2021 |\n| EUR \u20acSTR | CompoundedWithObservationShift | 2 BD | ECB |\n| GBP SONIA | CompoundedWithObservationShift | 5 BD | BoE |\n| JPY TONA | CompoundedInArrears | 2 BD | BoJ |\n\n# Reference\n\n- ISDA (2021). \"IBOR Fallbacks Supplement.\" Section 7.\n- ARRC (2020). \"SOFR: A User's Guide.\" Federal Reserve Bank of New York.\n- `docs/REFERENCES.md#andersen-piterbarg-interest-rate-modeling`\n- `docs/REFERENCES.md#isda-2006-definitions`",
      "oneOf": [
        {
          "const": "SimpleAverage",
          "description": "Arithmetic (non-compounded) average of daily overnight fixings,\nweighted by accrual days: `Rate = (\u03a3 r\u1d62\u00b7d\u1d62) / D`.\n\nThis is a fully supported convention. It is the correct choice for\ninstruments that contractually specify a simple-average overnight\nindex (some bilateral loans and older FRNs) rather than the\ncompounded ISDA 2021 convention. Use [`Self::CompoundedInArrears`]\nfor standard SOFR/ESTR/TONA legs.",
          "type": "string"
        },
        {
          "const": "CompoundedInArrears",
          "description": "Compounded in arrears with daily compounding (ISDA 2021 standard).\n\n```text\nRate = [\u220f(1 + r_i \u00d7 d_i/360) - 1] \u00d7 360/D\n```",
          "type": "string"
        },
        {
          "additionalProperties": false,
          "description": "Compounded in arrears with lookback (shift observation period).\n\nUses rates from `lookback_days` business days before each accrual date.",
          "properties": {
            "CompoundedWithLookback": {
              "additionalProperties": false,
              "properties": {
                "lookback_days": {
                  "description": "Number of business days to look back for rate observations.",
                  "format": "uint32",
                  "minimum": 0,
                  "type": "integer"
                }
              },
              "required": [
                "lookback_days"
              ],
              "type": "object"
            }
          },
          "required": [
            "CompoundedWithLookback"
          ],
          "type": "object"
        },
        {
          "additionalProperties": false,
          "description": "Compounded in arrears with lockout (rate cut-off near end of period).\n\nUses the rate from `lockout_days` business days before period end for all\nremaining days in the period. With fixings `b_1..b_n` (where `b_n` is one\nbusiness day before the exclusive period end), the cut-off fixing is\n`b_{n-lockout+1}` per ISDA 2021 Definitions \u00a77 (rate cut-off) and the\nARRC SOFR FRN conventions.",
          "properties": {
            "CompoundedWithLockout": {
              "additionalProperties": false,
              "properties": {
                "lockout_days": {
                  "description": "Number of business days before period end to freeze the rate.",
                  "format": "uint32",
                  "minimum": 0,
                  "type": "integer"
                }
              },
              "required": [
                "lockout_days"
              ],
              "type": "object"
            }
          },
          "required": [
            "CompoundedWithLockout"
          ],
          "type": "object"
        },
        {
          "additionalProperties": false,
          "description": "Compounded in arrears with observation shift.\n\nBoth observation dates AND weights are shifted back by `shift_days`\nbusiness days. This is the ISDA 2021 recommended convention for SOFR\nand the standard for GBP SONIA and EUR \u20acSTR.",
          "properties": {
            "CompoundedWithObservationShift": {
              "additionalProperties": false,
              "properties": {
                "shift_days": {
                  "description": "Number of business days to shift observations.",
                  "format": "uint32",
                  "minimum": 0,
                  "type": "integer"
                }
              },
              "required": [
                "shift_days"
              ],
              "type": "object"
            }
          },
          "required": [
            "CompoundedWithObservationShift"
          ],
          "type": "object"
        }
      ]
    },
    "OvernightIndexConstraintApplication": {
      "description": "Where overnight index floors/caps are applied for daily-compounded rates.",
      "oneOf": [
        {
          "const": "Daily",
          "description": "Apply index floors/caps to each sampled daily fixing before compounding.\n\nThis matches common floored SOFR loan conventions.",
          "type": "string"
        },
        {
          "const": "Period",
          "description": "Apply index floors/caps once to the compounded period index rate.\n\nThis preserves the historical period-level behavior for contracts that\nexplicitly define floors/caps on the period index rate.",
          "type": "string"
        }
      ]
    },
    "ProtectionWindow": {
      "description": "When the return-floor protection window applies.\n\nThe window defines the interval over which the issuer can trigger a\nfloor-protected early redemption. Outside this window the floor is\ninactive (the bond behaves as uncallable or follows its normal call\nschedule). The floor binds only on early issuer-called redemptions; it\nnever applies at maturity.",
      "oneOf": [
        {
          "const": "Full",
          "description": "From issue (or `as_of`) up to \u2014 but not including \u2014 maturity (default).\nThe floor applies to any early issuer-called redemption during the\nbond's life, but not to redemption at maturity.",
          "type": "string"
        },
        {
          "additionalProperties": false,
          "description": "Active only on or after this date (encodes a no-call period ending at\nmaturity). The floor is not applied to redemptions before `from`.",
          "properties": {
            "From": {
              "type": "string"
            }
          },
          "required": [
            "From"
          ],
          "type": "object"
        },
        {
          "additionalProperties": false,
          "description": "Explicit closed interval `[start, end]` (both ends inclusive). The floor\napplies only for redemptions with `start <= redemption_date <= end`.",
          "properties": {
            "Between": {
              "properties": {
                "end": {
                  "description": "Last date on which the floor-protected call window closes (inclusive).",
                  "type": "string"
                },
                "start": {
                  "description": "First date on which the floor-protected call window opens.",
                  "type": "string"
                }
              },
              "required": [
                "start",
                "end"
              ],
              "type": "object"
            }
          },
          "required": [
            "Between"
          ],
          "type": "object"
        }
      ]
    },
    "ReturnFloorKind": {
      "description": "Which return metric is guaranteed by the floor, and its target.\n\nUse [`ReturnFloorKind::Moic`] for money-multiple protection (common in\nleveraged loans and private credit) or [`ReturnFloorKind::Xirr`] for\nannualized IRR protection.",
      "oneOf": [
        {
          "additionalProperties": false,
          "description": "Minimum money-on-money multiple (e.g. `1.25` = 1.25\u00d7 invested capital).\n\nOn an early issuer-called redemption at time `t`, the redemption price is\nthe minimum amount such that `(received_cashflows + redemption) / V0 >=\nmultiple`, where `V0` is the invested capital defined by [`IssuePrice`].\nThe floor binds only on early redemptions, not at maturity.",
          "properties": {
            "Moic": {
              "format": "double",
              "type": "number"
            }
          },
          "required": [
            "Moic"
          ],
          "type": "object"
        },
        {
          "additionalProperties": false,
          "description": "Minimum annualized internal rate of return.\n\nOn an early issuer-called redemption at time `t`, the redemption price is\ncomputed so that the XIRR of all cashflows from issue equals the target\nrate. The floor binds only on early redemptions, not at maturity. Day\ncount defaults to Act/365F (matching `core::cashflow::xirr`) unless\noverridden via [`ReturnFloorSpec::day_count`].",
          "properties": {
            "Xirr": {
              "format": "double",
              "type": "number"
            }
          },
          "required": [
            "Xirr"
          ],
          "type": "object"
        }
      ]
    },
    "ReturnFloorSpec": {
      "additionalProperties": false,
      "description": "Guaranteed minimum-return call protection on a bond or loan.\n\nAttaching this spec declares that on any early issuer-called or prepaid\nredemption within the protection window, the redemption price will be\nfloored so the investor's realized return meets the target. This is the\nstandard private-credit loan model (often called a \"prepayment premium\" or\n\"call protection\" in credit agreements). The floor is anchored at the issue\ndate and issue price `V0`. The spec is lowered into a concrete call schedule\nat pricing time; see `bond/pricing/return_floor.rs`.\n\n**Call-protection only**: the floor applies to EARLY issuer redemptions\nwithin the [`ProtectionWindow`] and never at maturity. The held-to-maturity\npath is unfloored. Use [`crate::metrics::MetricId::MoicToWorst`] /\n[`crate::metrics::MetricId::XirrToWorst`] to see the honest worst-case\nreturn across all paths including the unfloored maturity path.\n\n# Mathematical Foundation\n\nLet:\n- `V0` = invested capital (issue price).\n- `t` = early-redemption date.\n- `cash_through(t)` = sum of positive cashflows received by the holder in\n  the half-open interval `(issue, t]` (coupons and amortization; excludes\n  the redemption itself).\n- `yf(a, b)` = year fraction from date `a` to date `b` under `Act/365F`.\n\n**MOIC floor** \u2014 minimum money-on-invested-capital multiple `m`:\n\n```text\nR(t) = m \u00b7 V0 \u2212 cash_through(t)\n```\n\nThe required redemption at `t` is `max(R(t), contractual_call(t), V0)`.\n\n**XIRR floor** \u2014 minimum annualized IRR `r`:\n\n```text\nR(t) = (1 + r)^yf(issue, t) \u00b7 (V0 \u2212 \u03a3_{q \u2264 t} coupon_q / (1 + r)^yf(issue, q))\n```\n\nThe day-count convention for `yf` defaults to `Act/365F`, matching\n[`finstack_quant_core::cashflow::xirr`] so the verification metrics\nreproduce the floor target exactly.\n\nBoth floors are then clamped to `max(R(t), 100.0)` (never below par) and\ndivided by the outstanding notional at `t`.\n\n# Limitations (v1)\n\n- **Floating-rate coupons**: forward-projected using the yield curve at\n  pricing time. Path-accurate LSMC (where rate paths determine both coupon\n  magnitudes and call-trigger probabilities simultaneously) is deferred to v2.\n- **Make-whole calls**: contractual make-whole provisions cannot compose\n  with a return floor in v1 \u2014 attempting this returns a validation error.\n  Make-whole effective prices are path-dependent and cannot be pre-computed\n  statically when lowering the floor.\n- **Amortizing bonds (to-worst)**: the `MoicToWorst` / `XirrToWorst`\n  metrics use the initial notional as the redemption basis rather than the\n  outstanding notional at the exit date. This is exact for bullet bonds but\n  overstates the redemption for amortizing structures (TODO v2).\n- **`min_moic` / `min_xirr` shortcuts**: these set\n  [`ProtectionWindow::Full`] (prepayable across the bond's entire life).\n  Narrow the window via [`ReturnFloorSpec::window`] if a no-call period\n  applies.\n\n# Invariants\n\n- MOIC multiple must be positive (`> 0`).\n- XIRR rate must be finite and greater than `-1` (i.e., `-100%`).\n- A [`ProtectionWindow::Between`] window must have `start < end`.\n\n# References\n\n- **MOIC**: Standard private-equity and private-credit return metric.\n  MOIC = total distributions / invested capital. See e.g. Rosenbaum, J. &\n  Pearl, J. (2013). *Investment Banking: Valuation, Leveraged Buyouts, and\n  Mergers & Acquisitions* (2nd ed.). Wiley Finance.\n- **XIRR / IRR**: Internal rate of return. See Brealey, R. A., Myers, S.\n  C. & Allen, F. (2023). *Principles of Corporate Finance* (14th ed.).\n  McGraw-Hill. Chapter 5 (\"Net Present Value and Other Investment Criteria\").\n- **Call-protection / prepayment premiums**: Standard private-credit\n  agreement term. LSTA (Loan Syndications and Trading Association).\n  *The Handbook of Loan Syndications and Trading* (2nd ed.). Chapter on\n  loan documentation and call protection.\n- **Act/365F day count**: ISDA 2006 Definitions, Section 4.16(f).\n\n# Examples\n\n```rust\nuse finstack_quant_valuations::instruments::fixed_income::bond::{\n    ReturnFloorSpec, IssuePrice,\n};\nuse finstack_quant_core::types::Rate;\n\n// 1.20\u00d7 MOIC floor at par, full protection window\nlet spec = ReturnFloorSpec::moic(1.20);\nassert!(spec.validate().is_ok());\n\n// 10% XIRR floor with 98 OID, validated\nlet spec = ReturnFloorSpec::xirr(Rate::from_percent(10.0))\n    .issue_price(IssuePrice::PctOfPar(98.0));\nassert!(spec.validate().is_ok());\n```\n\nAttach to a bond using the fluent builder:\n\n```rust,ignore\nuse finstack_quant_valuations::instruments::fixed_income::bond::{\n    Bond, ReturnFloorSpec, ProtectionWindow,\n};\nuse finstack_quant_core::currency::Currency;\nuse finstack_quant_core::money::Money;\nuse time::macros::date;\n\n// 5-year loan with 1.25\u00d7 MOIC floor active after a 2-year no-call period.\nlet loan = Bond::fixed(\n    \"LOAN-001\",\n    Money::new(1_000_000.0, Currency::USD),\n    0.10,\n    date!(2025 - 01 - 01),\n    date!(2030 - 01 - 01),\n    \"USD-OIS\",\n)?\n.with_return_floor(\n    ReturnFloorSpec::moic(1.25)\n        .window(ProtectionWindow::From(date!(2027 - 01 - 01))),\n);\n# Ok::<(), Box<dyn std::error::Error>>(())\n```",
      "properties": {
        "day_count": {
          "anyOf": [
            {
              "$ref": "https://finstack_quant.dev/schemas/common/1/day_count.schema.json"
            },
            {
              "type": "null"
            }
          ],
          "description": "Day count convention for XIRR discounting. Defaults to Act/365F\n(matching `core::cashflow::xirr`) when `None`. Ignored for MOIC floors."
        },
        "issue_price": {
          "$ref": "#/$defs/IssuePrice",
          "default": "Par",
          "description": "Issue price = invested capital `V0` (amount funded at issue). Default: par."
        },
        "kind": {
          "$ref": "#/$defs/ReturnFloorKind",
          "description": "Which return metric is guaranteed, and its target."
        },
        "window": {
          "$ref": "#/$defs/ProtectionWindow",
          "default": "Full",
          "description": "Protection window. Default: [`ProtectionWindow::Full`]."
        }
      },
      "required": [
        "kind"
      ],
      "type": "object"
    },
    "StepUpCouponSpec": {
      "additionalProperties": false,
      "description": "Step-up/step-down coupon specification.\n\nDefines a coupon that changes rate at specified dates, commonly used\nin bank capital instruments (AT1/Tier 2) and some agency bonds.\n\nThe rate for each coupon period is determined by the last step date\nthat falls on or before the period start date. If no step has occurred,\nthe initial rate is used.\n\n# Examples\n\n```rust\nuse finstack_quant_core::dates::{Date, DayCount, Tenor, BusinessDayConvention, StubKind};\nuse finstack_quant_cashflows::builder::{CouponType, ScheduleParams, StepUpCouponSpec};\nuse rust_decimal_macros::dec;\nuse time::Month;\n\nlet spec = StepUpCouponSpec {\n    coupon_type: CouponType::Cash,\n    initial_rate: dec!(0.03),\n    step_schedule: vec![\n        (Date::from_calendar_date(2027, Month::January, 1).unwrap(), dec!(0.04)),\n        (Date::from_calendar_date(2029, Month::January, 1).unwrap(), dec!(0.05)),\n    ],\n    schedule: ScheduleParams {\n        freq: Tenor::semi_annual(),\n        dc: DayCount::Thirty360,\n        bdc: BusinessDayConvention::Following,\n        calendar_id: \"weekends_only\".to_string(),\n        stub: StubKind::None,\n        end_of_month: false,\n        payment_lag_days: 0,\n        adjust_accrual_dates: false,\n    },\n};\n```",
      "properties": {
        "adjust_accrual_dates": {
          "description": "Whether accrual-period boundaries are business-day adjusted with `bdc`.\n\n- `false` (default, bond convention): accrual periods run between the\n  unadjusted schedule anchors; only payment dates roll.\n- `true` (swap convention, ISDA 2006 \u00a74.10 / ARRC SOFR conventions):\n  both accrual-period boundaries are rolled with `bdc` before year\n  fractions and overnight observation windows are computed. The swap\n  presets ([`Self::usd_sofr_swap`], [`Self::eur_estr_swap`],\n  [`Self::gbp_sonia_swap`], [`Self::jpy_tona_swap`]) set this to\n  `true`.\n\nSerialized only when `true`, so existing wire payloads are unchanged.",
          "type": "boolean"
        },
        "bdc": {
          "$ref": "https://finstack_quant.dev/schemas/common/1/business_day_convention.schema.json",
          "default": "modified_following",
          "description": "Business-day convention applied when rolling **payment dates** onto\nvalid business days.\n\nAccrual boundaries are left unadjusted (bond/ICMA convention) unless\n[`Self::adjust_accrual_dates`] is `true`, in which case the same\nconvention also rolls both accrual-period boundaries (swap/ISDA 2006\n\u00a74.10 convention)."
        },
        "calendar_id": {
          "description": "Holiday calendar identifier used together with `bdc`.\n\nUse `\"weekends_only\"` when only Saturday/Sunday adjustment is needed.",
          "type": "string"
        },
        "coupon_type": {
          "$ref": "#/$defs/CouponType",
          "default": "Cash",
          "description": "Coupon type (Cash/PIK/Split)."
        },
        "dc": {
          "$ref": "https://finstack_quant.dev/schemas/common/1/day_count.schema.json",
          "description": "Day-count convention used to convert each generated accrual period into a\nyear fraction."
        },
        "end_of_month": {
          "default": false,
          "description": "Whether end-of-month rolling should be preserved when generating the\nschedule.",
          "type": "boolean"
        },
        "freq": {
          "$ref": "https://finstack_quant.dev/schemas/common/1/tenor.schema.json",
          "description": "Accrual and payment frequency used to generate the schedule boundaries."
        },
        "initial_rate": {
          "description": "Initial coupon rate (annual, decimal). Used until the first step date.",
          "pattern": "^-?\\d+(\\.\\d+)?([eE][+-]?\\d+)?$",
          "type": [
            "string",
            "number"
          ]
        },
        "payment_lag_days": {
          "default": 0,
          "description": "Payment lag in business days after the adjusted accrual end date.",
          "format": "int32",
          "type": "integer"
        },
        "step_schedule": {
          "description": "Step schedule: (effective_date, new_rate). Must be sorted by date.\nEach entry sets the rate from that date forward until the next step.\n\n**Date convention:** `effective_date` is compared against each\naccrual period's *unadjusted* `accrual_start`. Specify dates as\nunadjusted accrual-period boundaries (typically the issue date plus\ninteger multiples of `freq`); business-day adjustment is not\napplied here. The rate is set at accrual start (per market\nconvention for step-up bonds).",
          "items": {
            "maxItems": 2,
            "minItems": 2,
            "prefixItems": [
              {
                "type": "string"
              },
              {
                "pattern": "^-?\\d+(\\.\\d+)?([eE][+-]?\\d+)?$",
                "type": [
                  "string",
                  "number"
                ]
              }
            ],
            "type": "array"
          },
          "type": "array"
        },
        "stub": {
          "$ref": "#/$defs/StubKind",
          "default": "ShortFront",
          "description": "Stub-handling rule used when the start/end dates do not fit an exact\nwhole number of periods."
        }
      },
      "required": [
        "initial_rate",
        "step_schedule",
        "freq",
        "dc",
        "calendar_id"
      ],
      "type": "object"
    },
    "StubKind": {
      "description": "Stub period handling when start/end dates don't align with payment frequency.\n\nControls how schedules are generated when the start and end dates don't\ndivide evenly by the payment frequency, resulting in an irregular period\n(stub) at the beginning or end of the schedule.\n\n# Variants\n\n- **`None`**: No stub allowed (default). Generates regular periods from\n  start to end and returns an error\n  ([`InputError::NonIntegerScheduleTenor`]) when the dates don't divide\n  evenly by the frequency. Use a stub variant for misaligned schedules.\n\n[`InputError::NonIntegerScheduleTenor`]: crate::error::InputError::NonIntegerScheduleTenor\n- **`ShortFront`**: Short stub period at the start. Schedule is built\n  backward from the end date, creating a short first period.\n- **`ShortBack`**: Short stub period at the end. Schedule is built forward\n  from the start date, creating a short final period.\n- **`LongFront`**: Long stub period at the start. Combines the first two\n  periods into a single longer period.\n- **`LongBack`**: Long stub period at the end. Combines the last two periods\n  into a single longer period.\n\n# Financial Context\n\nStub conventions are important for:\n- Interest accrual calculations (short/long first coupons)\n- Cash flow present value computations\n- Matching market conventions for specific instruments\n\n# Examples\n\n```rust\nuse finstack_quant_core::dates::{ScheduleBuilder, Tenor, StubKind};\nuse time::{Date, Month};\n\nlet start = Date::from_calendar_date(2025, Month::January, 10)?;\nlet end = Date::from_calendar_date(2025, Month::December, 15)?;\n\n// Short stub at front\nlet sched = ScheduleBuilder::new(start, end)?\n    .frequency(Tenor::quarterly())\n    .stub_rule(StubKind::ShortFront)\n    .build()?;\n# Ok::<(), Box<dyn std::error::Error>>(())\n```\n\n# See Also\n\n- [`ScheduleBuilder::stub_rule`] to configure stub behavior",
      "oneOf": [
        {
          "const": "None",
          "description": "No stub allowed: start/end must align exactly with the frequency,\notherwise schedule generation returns an error.",
          "type": "string"
        },
        {
          "const": "ShortFront",
          "description": "Short stub period at the beginning of the schedule.",
          "type": "string"
        },
        {
          "const": "ShortBack",
          "description": "Short stub period at the end of the schedule (final step truncated to maturity).",
          "type": "string"
        },
        {
          "const": "LongFront",
          "description": "Long stub period at the beginning of the schedule.",
          "type": "string"
        },
        {
          "const": "LongBack",
          "description": "Long stub period at the end of the schedule (merges final two periods).",
          "type": "string"
        }
      ]
    }
  },
  "$id": "https://finstack_quant.dev/schemas/instrument/1/fixed_income/bond.schema.json",
  "$schema": "https://json-schema.org/draft/2020-12/schema",
  "additionalProperties": false,
  "description": "Fixed income bond instrument with fixed, floating, or amortizing cashflows. Use `issue_date` as the canonical issue field; `pricing_overrides.quoted_clean_price` may be supplied for market-price-driven validation examples.",
  "examples": [
    {
      "instrument": {
        "spec": {
          "attributes": {},
          "call_put": null,
          "cashflow_spec": {
            "Fixed": {
              "bdc": "following",
              "calendar_id": "sifma",
              "coupon_type": "Cash",
              "dc": "ActActIsma",
              "end_of_month": false,
              "freq": {
                "count": 6,
                "unit": "months"
              },
              "payment_lag_days": 0,
              "rate": "0.0425",
              "stub": "None"
            }
          },
          "credit_curve_id": null,
          "discount_curve_id": "USD-TREASURY",
          "ex_coupon_calendar_id": "sifma",
          "ex_coupon_days": 0,
          "id": "US912828XG33",
          "issue_date": "2024-01-15",
          "maturity": "2034-01-15",
          "notional": {
            "amount": "1000000",
            "currency": "USD"
          },
          "pricing_overrides": {
            "adaptive_bumps": false,
            "call_friction_cents": null,
            "cds_quote_bp": null,
            "credit_spread_bump_bp": null,
            "implied_volatility": null,
            "mc_seed_scenario": null,
            "mean_reversion": null,
            "quoted_clean_price": 98.75,
            "rate_bump_bp": null,
            "rho_bump_decimal": null,
            "spot_bump_pct": null,
            "theta_period": null,
            "tree_steps": null,
            "upfront_payment": null,
            "use_gobet_miri": false,
            "vega_bump_decimal": null,
            "vol_bump_pct": null,
            "vol_surface_extrapolation": "error",
            "ytm_bump_decimal": null
          },
          "settlement_days": 1
        },
        "type": "bond"
      },
      "schema": "finstack_quant.instrument/1"
    },
    {
      "instrument": {
        "spec": {
          "attributes": {},
          "call_put": null,
          "cashflow_spec": {
            "Floating": {
              "bdc": "modified_following",
              "calendar_id": "weekends_only",
              "coupon_type": "Cash",
              "dc": "Act360",
              "end_of_month": false,
              "freq": {
                "count": 3,
                "unit": "months"
              },
              "payment_lag_days": 0,
              "rate_spec": {
                "all_in_cap_bp": null,
                "all_in_floor_bp": null,
                "fixing_calendar_id": null,
                "gearing": "1",
                "gearing_includes_spread": true,
                "index_cap_bp": null,
                "index_floor_bp": "0",
                "index_id": "USD-SOFR-3M",
                "reset_freq": {
                  "count": 3,
                  "unit": "months"
                },
                "reset_lag_days": 2,
                "spread_bp": "150"
              },
              "stub": "ShortFront"
            }
          },
          "credit_curve_id": null,
          "discount_curve_id": "USD-OIS",
          "ex_coupon_days": 0,
          "id": "FRN-USD-SOFR-5Y",
          "issue_date": "2024-01-15",
          "maturity": "2029-01-15",
          "notional": {
            "amount": "1000000",
            "currency": "USD"
          },
          "pricing_overrides": {
            "adaptive_bumps": false,
            "call_friction_cents": null,
            "cds_quote_bp": null,
            "credit_spread_bump_bp": null,
            "implied_volatility": null,
            "mc_seed_scenario": null,
            "mean_reversion": null,
            "quoted_clean_price": null,
            "rate_bump_bp": null,
            "rho_bump_decimal": null,
            "spot_bump_pct": null,
            "theta_period": null,
            "tree_steps": null,
            "upfront_payment": null,
            "use_gobet_miri": false,
            "vega_bump_decimal": null,
            "vol_bump_pct": null,
            "vol_surface_extrapolation": "error",
            "ytm_bump_decimal": null
          },
          "settlement_days": 2
        },
        "type": "bond"
      },
      "schema": "finstack_quant.instrument/1"
    },
    {
      "instrument": {
        "spec": {
          "attributes": {},
          "call_put": {
            "calls": [
              {
                "end_date": "2027-01-15",
                "price_pct_of_par": 103.0,
                "start_date": "2027-01-15"
              },
              {
                "end_date": "2029-01-15",
                "price_pct_of_par": 101.0,
                "start_date": "2029-01-15"
              },
              {
                "end_date": "2031-01-15",
                "price_pct_of_par": 100.0,
                "start_date": "2031-01-15"
              }
            ],
            "puts": []
          },
          "cashflow_spec": {
            "Fixed": {
              "bdc": "following",
              "calendar_id": "weekends_only",
              "coupon_type": "Cash",
              "dc": "Thirty360",
              "end_of_month": false,
              "freq": {
                "count": 6,
                "unit": "months"
              },
              "payment_lag_days": 0,
              "rate": "0.05",
              "stub": "None"
            }
          },
          "credit_curve_id": null,
          "discount_curve_id": "USD-OIS",
          "ex_coupon_days": 0,
          "id": "CALLABLE-USD-10Y",
          "issue_date": "2024-01-15",
          "maturity": "2034-01-15",
          "notional": {
            "amount": "1000000",
            "currency": "USD"
          },
          "pricing_overrides": {
            "adaptive_bumps": false,
            "call_friction_cents": null,
            "cds_quote_bp": null,
            "credit_spread_bump_bp": null,
            "implied_volatility": null,
            "mc_seed_scenario": null,
            "mean_reversion": null,
            "quoted_clean_price": null,
            "rate_bump_bp": null,
            "rho_bump_decimal": null,
            "spot_bump_pct": null,
            "theta_period": null,
            "tree_steps": null,
            "upfront_payment": null,
            "use_gobet_miri": false,
            "vega_bump_decimal": null,
            "vol_bump_pct": null,
            "vol_surface_extrapolation": "error",
            "ytm_bump_decimal": null
          },
          "settlement_days": 2
        },
        "type": "bond"
      },
      "schema": "finstack_quant.instrument/1"
    },
    {
      "instrument": {
        "spec": {
          "attributes": {},
          "call_put": null,
          "cashflow_spec": {
            "Amortizing": {
              "base": {
                "Fixed": {
                  "bdc": "modified_following",
                  "calendar_id": "weekends_only",
                  "coupon_type": "Cash",
                  "dc": "Thirty360",
                  "end_of_month": false,
                  "freq": {
                    "count": 6,
                    "unit": "months"
                  },
                  "payment_lag_days": 0,
                  "rate": "0.04",
                  "stub": "ShortFront"
                }
              },
              "schedule": {
                "LinearTo": {
                  "final_notional": {
                    "amount": "200000",
                    "currency": "USD"
                  }
                }
              }
            }
          },
          "credit_curve_id": null,
          "discount_curve_id": "USD-OIS",
          "ex_coupon_days": 0,
          "id": "AMORT-USD-5Y",
          "issue_date": "2024-01-15",
          "maturity": "2029-01-15",
          "notional": {
            "amount": "1000000",
            "currency": "USD"
          },
          "pricing_overrides": {
            "adaptive_bumps": false,
            "call_friction_cents": null,
            "cds_quote_bp": null,
            "credit_spread_bump_bp": null,
            "implied_volatility": null,
            "mc_seed_scenario": null,
            "mean_reversion": null,
            "quoted_clean_price": null,
            "rate_bump_bp": null,
            "rho_bump_decimal": null,
            "spot_bump_pct": null,
            "theta_period": null,
            "tree_steps": null,
            "upfront_payment": null,
            "use_gobet_miri": false,
            "vega_bump_decimal": null,
            "vol_bump_pct": null,
            "vol_surface_extrapolation": "error",
            "ytm_bump_decimal": null
          },
          "settlement_days": 2
        },
        "type": "bond"
      },
      "schema": "finstack_quant.instrument/1"
    }
  ],
  "properties": {
    "instrument": {
      "additionalProperties": false,
      "description": "The Bond instrument definition",
      "properties": {
        "spec": {
          "properties": {
            "accrual_method": {
              "$ref": "#/$defs/AccrualMethod",
              "default": "Linear",
              "description": "Accrual method for interest calculation between coupon dates.\n\nDetermines how accrued interest is calculated:\n- `Linear` (default): Simple interest interpolation (most bonds)\n- `Compounded`: Actuarial accrual per ICMA Rule 251 (some European bonds)\n\nFor inflation-linked bonds (TIPS, UK Linkers), use the dedicated\n`InflationLinkedBond` instrument which handles index-ratio accrual."
            },
            "attributes": {
              "$ref": "https://finstack_quant.dev/schemas/common/1/attributes.schema.json",
              "description": "Attributes for scenario selection and tagging."
            },
            "call_put": {
              "anyOf": [
                {
                  "$ref": "#/$defs/CallPutSchedule"
                },
                {
                  "type": "null"
                }
              ],
              "description": "Optional call/put schedule (dates and redemption prices as % of par amount)."
            },
            "cashflow_spec": {
              "$ref": "#/$defs/CashflowSpec",
              "description": "Cashflow specification (fixed, floating, or amortizing)."
            },
            "credit_curve_id": {
              "anyOf": [
                {
                  "$ref": "https://finstack_quant.dev/schemas/common/1/id.schema.json"
                },
                {
                  "type": "null"
                }
              ],
              "description": "Optional credit curve identifier (default intensity). When present,\ncredit-rate pricing is enabled."
            },
            "custom_cashflows": {
              "anyOf": [
                {
                  "$ref": "#/$defs/CashFlowSchedule"
                },
                {
                  "type": "null"
                }
              ],
              "description": "Optional pre-built cashflow schedule. If provided, this will be used instead of\ngenerating cashflows from the cashflow_spec."
            },
            "discount_curve_id": {
              "$ref": "https://finstack_quant.dev/schemas/common/1/id.schema.json",
              "description": "Discount curve identifier for pricing."
            },
            "ex_coupon_calendar_id": {
              "description": "Calendar identifier for ex-coupon day counting.",
              "type": [
                "string",
                "null"
              ]
            },
            "ex_coupon_days": {
              "default": 0,
              "description": "Number of ex-coupon days before coupon date.",
              "format": "uint32",
              "minimum": 0,
              "type": "integer"
            },
            "forward_curve_id": {
              "anyOf": [
                {
                  "$ref": "https://finstack_quant.dev/schemas/common/1/id.schema.json"
                },
                {
                  "type": "null"
                }
              ],
              "description": "Optional forward curve identifier for projected floating or asset-swap legs."
            },
            "funding_curve_id": {
              "anyOf": [
                {
                  "$ref": "https://finstack_quant.dev/schemas/common/1/id.schema.json"
                },
                {
                  "type": "null"
                }
              ],
              "description": "Optional funding/repo curve for carry cost computation."
            },
            "id": {
              "$ref": "https://finstack_quant.dev/schemas/common/1/id.schema.json",
              "description": "Unique identifier for the bond."
            },
            "issue_date": {
              "description": "Issue date of the bond.",
              "format": "date",
              "type": "string"
            },
            "maturity": {
              "description": "Maturity date of the bond.",
              "format": "date",
              "type": "string"
            },
            "notional": {
              "$ref": "https://finstack_quant.dev/schemas/common/1/money.schema.json",
              "description": "Principal amount of the bond."
            },
            "pricing_overrides": {
              "$ref": "https://finstack_quant.dev/schemas/common/1/pricing_overrides.schema.json",
              "default": {
                "adaptive_bumps": false,
                "call_friction_cents": null,
                "cds_act360_include_last_day": false,
                "cds_aod_half_day_bias": false,
                "credit_spread_bump_bp": null,
                "mc_seed_scenario": null,
                "mean_reversion": null,
                "oas_price_basis": "settlement_dirty",
                "oas_quote_compounding": "continuous",
                "rate_bump_bp": null,
                "rho_bump_decimal": null,
                "spot_bump_pct": null,
                "theta_period": null,
                "tree_steps": null,
                "use_gobet_miri": false,
                "vega_bump_decimal": null,
                "vol_bump_pct": null,
                "vol_surface_extrapolation": "error",
                "ytm_bump_decimal": null
              },
              "description": "Pricing overrides (including quoted clean price)"
            },
            "return_floor": {
              "anyOf": [
                {
                  "$ref": "#/$defs/ReturnFloorSpec"
                },
                {
                  "type": "null"
                }
              ],
              "description": "Optional guaranteed minimum-return (\"return floor\") call protection.\n\nWhen present, the bond is treated as prepayable across the protection\nwindow with redemption floored so the investor meets the target MOIC/XIRR.\nLowered into `call_put` at pricing time."
            },
            "settlement_days": {
              "default": 0,
              "description": "Number of settlement days after trade date (e.g., 2 for T+2).",
              "format": "uint32",
              "minimum": 0,
              "type": "integer"
            }
          },
          "required": [
            "id",
            "notional",
            "issue_date",
            "maturity",
            "cashflow_spec",
            "discount_curve_id",
            "attributes"
          ],
          "type": "object"
        },
        "type": {
          "const": "bond",
          "type": "string"
        }
      },
      "required": [
        "type",
        "spec"
      ],
      "type": "object"
    },
    "schema": {
      "const": "finstack_quant.instrument/1",
      "description": "Schema version identifier",
      "type": "string"
    }
  },
  "required": [
    "schema",
    "instrument"
  ],
  "title": "Bond",
  "type": "object"
}
